<?xml version="1.0" encoding="utf-8"?>
<DocPropertyEnumeration xmlns:xsi="http://www.w3.org/2001/XMLSchema-instance" Name="PEnum_AirTerminalDischargeDirection" UniqueId="37c22530-f179-46fc-8f37-cb715c0bdfb9">
	<Constants>
		<DocPropertyConstant xsi:nil="true" href="PARALLEL_0rfWQRmgPF8xt1dUK$8E5d" />
		<DocPropertyConstant xsi:nil="true" href="PERPENDICULAR_17nOUuhd52gfjIIBTbLIpZ" />
		<DocPropertyConstant xsi:nil="true" href="ADJUSTABLE_1Wp38pa49A2fdY6R$egevz" />
		<DocPropertyConstant xsi:nil="true" href="OTHER_06qnO51e1EUP_49WJicIYq" />
		<DocPropertyConstant xsi:nil="true" href="NOTKNOWN_2Gspfh8Kr59fWfo_YZpF$E" />
		<DocPropertyConstant xsi:nil="true" href="UNSET_3q97doNp5Bywcowyt_pefo" />
	</Constants>
</DocPropertyEnumeration>

